serey/__init__.py
serey/account.py
serey/amount.py
serey/block.py
serey/blockchain.py
serey/blog.py
serey/cli.py
serey/commit.py
serey/converter.py
serey/dex.py
serey/instance.py
serey/post.py
serey/profile.py
serey/serey.py
serey/sereyd.py
serey/transactionbuilder.py
serey/utils.py
serey/wallet.py
serey/witness.py
sereybase/__init__.py
sereybase/account.py
sereybase/aes.py
sereybase/base58.py
sereybase/bip38.py
sereybase/chains.py
sereybase/dictionary.py
sereybase/exceptions.py
sereybase/http_client.py
sereybase/memo.py
sereybase/operationids.py
sereybase/operations.py
sereybase/storage.py
sereybase/transactions.py
sereybase/types.py
sereybase/utils.py
serey-1.0.0.dist-info/LICENSE
serey-1.0.0.dist-info/METADATA
serey-1.0.0.dist-info/WHEEL
serey-1.0.0.dist-info/entry_points.txt
serey-1.0.0.dist-info/top_level.txt
serey-1.0.0.dist-info/RECORD
